ultimate_trimmer/__init__.py
ultimate_trimmer/comment.py
ultimate_trimmer/core.py
ultimate_trimmer/logger.py
ultimate_trimmer/option.py
ultimate_trimmer/trim_info.py
ultimate_trimmer/utils.py
ultimate_trimmer/commands/__init__.py
ultimate_trimmer/commands/getComment.py
ultimate_trimmer/commands/trim.py
ultimate_trimmer-1.1.0.dist-info/LICENSE
ultimate_trimmer-1.1.0.dist-info/METADATA
ultimate_trimmer-1.1.0.dist-info/WHEEL
ultimate_trimmer-1.1.0.dist-info/entry_points.txt
ultimate_trimmer-1.1.0.dist-info/top_level.txt
ultimate_trimmer-1.1.0.dist-info/RECORD
