Metadata-Version: 2.1
Name: ultimate-trimmer
Version: 1.1.0
Summary: To trim a specified section in CSV files
Home-page: https://github.com/iikyara/UltimateTrimmer
Author: iikyara
Author-email: baaninreo@gmail.com
License: "MIT"
Keywords: ultimatetrimmer,ultimate_trimmer
Platform: UNKNOWN
Classifier: Programming Language :: Python :: 3.6
Classifier: License :: OSI Approved :: MIT License
License-File: LICENSE
Requires-Dist: moviepy (>=1.0.3)
Requires-Dist: chardet (>=4.0.0)
